qcalibrateremote/__init__.py
qcalibrateremote/_auth.py
qcalibrateremote/_browser.py
qcalibrateremote/_buffer.py
qcalibrateremote/_client.py
qcalibrateremote/_endpoint.py
qcalibrateremote/_fom.py
qcalibrateremote/_observer.py
qcalibrateremote/builders.py
qcalibrateremote/_grpc/Protocol.md
qcalibrateremote/_grpc/__init__.py
qcalibrateremote/_grpc/_auth.py
qcalibrateremote/_grpc/_run_codegen.py
qcalibrateremote/_grpc/qcalibrate.proto
qcalibrateremote/_grpc/qcalibrate_pb2.py
qcalibrateremote/_grpc/qcalibrate_pb2_grpc.py
qcalibrateremote-0.2.3.dist-info/LICENSE.txt
qcalibrateremote-0.2.3.dist-info/METADATA
qcalibrateremote-0.2.3.dist-info/WHEEL
qcalibrateremote-0.2.3.dist-info/top_level.txt
qcalibrateremote-0.2.3.dist-info/RECORD
