Metadata-Version: 2.1
Name: qcalibrateremote
Version: 0.2.3
Summary: QCalibrate remote interface
Home-page: https://iffgit.fz-juelich.de/qruise/qcalibrate
Author: Roman Razilov
Author-email: r.razilov@fz-juelich.de
License: Apache 2.0
Project-URL: Documentation, https://iffgit.fz-juelich.de/qruise/qcalibrate/-/wikis/home
Project-URL: Source, https://iffgit.fz-juelich.de/qruise/qcalibrate
Platform: any
Classifier: Development Status :: 2 - Pre-Alpha
Classifier: Programming Language :: Python
Requires-Python: >=3.8
License-File: LICENSE.txt
Requires-Dist: cuid
Requires-Dist: grpcio (<2.0,>=1.34.1)
Requires-Dist: grpcio-tools (<2.0,>=1.34.1)
Requires-Dist: icecream
Requires-Dist: numpy
Requires-Dist: PyYAML
Requires-Dist: importlib-metadata ; python_version < "3.8"
Provides-Extra: testing
Requires-Dist: setuptools ; extra == 'testing'
Requires-Dist: pytest ; extra == 'testing'
Requires-Dist: pytest-cov ; extra == 'testing'
